omero_webtest/__init__.py
omero_webtest/apps.py
omero_webtest/urls.py
omero_webtest/views.py
omero_webtest/static/webtest/img/background.png
omero_webtest/static/webtest/img/channel_overlay-16.png
omero_webtest/static/webtest/img/figure_icon-16.png
omero_webtest/static/webtest/img/channel_overlay/minus12.png
omero_webtest/static/webtest/img/channel_overlay/plus12.png
omero_webtest/static/webtest/js/image_dims.js
omero_webtest/templates/webtest/dataset.html
omero_webtest/templates/webtest/index.html
omero_webtest/templates/webtest/stack_preview.html
omero_webtest/templates/webtest/demo_viewers/channel_overlay_viewer.html
omero_webtest/templates/webtest/demo_viewers/image_dimensions.html
omero_webtest/templates/webtest/demo_viewers/image_rois.html
omero_webtest/templates/webtest/demo_viewers/render_performance.html
omero_webtest/templates/webtest/demo_viewers/split_view_figure.html
omero_webtest/templates/webtest/demo_viewers/static_example.html
omero_webtest/templates/webtest/examples/embed_big_image.html
omero_webtest/templates/webtest/examples/embed_external_rois.html
omero_webtest/templates/webtest/examples/embed_viewer.html
omero_webtest/templates/webtest/examples/plate_viewer.html
omero_webtest/templates/webtest/util/add_annotations.html
omero_webtest/templates/webtest/webclient_plugins/center_plugin.fullviewer.html
omero_webtest/templates/webtest/webclient_plugins/center_plugin.fullviewer.js.html
omero_webtest/templates/webtest/webclient_plugins/center_plugin.overlay.js.html
omero_webtest/templates/webtest/webclient_plugins/center_plugin.splitview.js.html
omero_webtest/templates/webtest/webclient_plugins/dataset_split_include.html
omero_webtest/templates/webtest/webclient_plugins/dataset_split_view.html
omero_webtest/templates/webtest/webclient_plugins/right_plugin.rois.js.html
omero_webtest/templates/webtest/webclient_plugins/split_view_fig_include.html
omero_webtest/templates/webtest/webclient_plugins/split_view_figure.html
omero_webtest-0.4.2.dist-info/LICENSE
omero_webtest-0.4.2.dist-info/METADATA
omero_webtest-0.4.2.dist-info/WHEEL
omero_webtest-0.4.2.dist-info/top_level.txt
omero_webtest-0.4.2.dist-info/RECORD
