Metadata-Version: 2.1
Name: omero-webtest
Version: 0.4.2
Summary: A Python plugin for OMERO.web
Home-page: https://github.com/ome/omero-webtest
Author: The Open Microscopy Team
Author-email: ome-devel@lists.openmicroscopy.org.uk
License: AGPL-3.0
Download-URL: https://github.com/ome/omero-webtest/archive/v0.4.2.tar.gz
Keywords: OMERO.web,plugin
Platform: UNKNOWN
Classifier: Development Status :: 5 - Production/Stable
Classifier: Environment :: Web Environment
Classifier: Framework :: Django
Classifier: Intended Audience :: Developers
Classifier: Natural Language :: English
Classifier: Operating System :: OS Independent
Classifier: Programming Language :: JavaScript
Classifier: Programming Language :: Python :: 3
Classifier: Topic :: Internet :: WWW/HTTP
Classifier: Topic :: Internet :: WWW/HTTP :: Dynamic Content
Classifier: Topic :: Internet :: WWW/HTTP :: WSGI
Classifier: Topic :: Scientific/Engineering :: Visualization
Classifier: Topic :: Software Development :: Libraries :: Application Frameworks
Classifier: Topic :: Software Development :: Testing
Classifier: Topic :: Text Processing :: Markup :: HTML
Requires-Python: >=3
License-File: LICENSE
Requires-Dist: omero-web (>=5.6.0)
